a2a_mcp_server.py
persistence_utils.py
common/__init__.py
common/types.py
common/client/__init__.py
common/client/card_resolver.py
common/client/client.py
common/server/__init__.py
common/server/server.py
common/server/task_manager.py
common/server/utils.py
common/utils/in_memory_cache.py
common/utils/push_notification_auth.py
a2a_mcp_server-0.1.5.dist-info/METADATA
a2a_mcp_server-0.1.5.dist-info/WHEEL
a2a_mcp_server-0.1.5.dist-info/entry_points.txt
a2a_mcp_server-0.1.5.dist-info/licenses/LICENSE
a2a_mcp_server-0.1.5.dist-info/RECORD
