Metadata-Version: 2.4
Name: a2a_mcp_server
Version: 0.1.5
Summary: A bridge server that connects Model Context Protocol (MCP) with Agent-to-Agent (A2A) protocol
Project-URL: Homepage, https://github.com/GongRzhe/A2A-MCP-Server
Project-URL: Bug Tracker, https://github.com/GongRzhe/A2A-MCP-Server/issues
Project-URL: Repository, https://github.com/GongRzhe/A2A-MCP-Server
Project-URL: Documentation, https://github.com/GongRzhe/A2A-MCP-Server/blob/main/README.md
Author-email: GongRzhe <gongrzhe@gmail.com>
Maintainer-email: GongRzhe <gongrzhe@gmail.com>
License: Apache-2.0
License-File: LICENSE
Keywords: A2A,AI,Agent-to-Agent,LLM,MCP,Model Context Protocol
Classifier: Development Status :: 4 - Beta
Classifier: Intended Audience :: Developers
Classifier: License :: OSI Approved :: Apache Software License
Classifier: Programming Language :: Python :: 3
Classifier: Programming Language :: Python :: 3.11
Classifier: Topic :: Scientific/Engineering :: Artificial Intelligence
Classifier: Topic :: Software Development :: Libraries :: Python Modules
Requires-Python: >=3.11
Requires-Dist: fastmcp>=2.8.1
Requires-Dist: httpx-sse>=0.4.0
Requires-Dist: httpx>=0.28.1
Requires-Dist: jwcrypto>=1.5.6
Requires-Dist: pydantic>=2.10.6
Requires-Dist: pyjwt>=2.10.1
Requires-Dist: sse-starlette>=2.2.1
Requires-Dist: starlette>=0.46.1
Requires-Dist: typing-extensions>=4.12.2
Requires-Dist: uvicorn>=0.34.0
Provides-Extra: dev
Requires-Dist: pytest-mock>=3.14.0; extra == 'dev'
Requires-Dist: pytest>=8.3.5; extra == 'dev'
Requires-Dist: ruff>=0.11.2; extra == 'dev'
